{
  "schemaVersion": "1.0",
  "id": "ebaa0e86-5674-4b8c-b796-a5036a946b00",
  "name": "Application Control (IPS) (Reset)",
  "description": "Fortinet detection - Application control (IPS) (reset)",
  "riskLevel": "low",
  "scope": "endpoint",
  "rules": [
    {
      "id": "67c25299-7988-4285-8441-3a0844fae587",
      "name": "Application Control (IPS) (Reset)",
      "score": 1
    }
  ],
  "threshold": {
    "targetScore": 1,
    "withinSeconds": 3000,
    "dedupSeconds": 3000
  },
  "requiredProducts": [
    [
      "tlc|Fortinet"
    ]
  ],
  "tags": [],
  "playbooks": [
    {
      "id": "a4c36882-115b-4296-a5e3-051fc303e0ca",
      "name": "Default Playbook",
      "provider": "WORKBENCH",
      "type": "DETECTION"
    },
    {
      "id": "f87e38bc-b0a9-4997-8b6a-d0762a7bcace",
      "name": "Generic file/ip/url/email investigation",
      "provider": "AIR",
      "type": "AUTOMATED_RESPONSE"
    }
  ],
  "visibleLevel": 51,
  "globalModel": true,
  "silent": true,
  "author": "James Vargas",
  "team": "DDI",
  "date": "2024/12/04",
  "lastUpdate": "2025-01-06T03:41:40.000Z"
}