{
  "schemaVersion": "1.0",
  "id": "0123dd9a-9821-42d5-a4c5-1cdeebe6ef0b",
  "name": "AWS VPC DHCP Options Association Modified",
  "description": "Change in DHCP options associated with a VPC, potentially altering DNS or network configurations.",
  "riskLevel": "medium",
  "scope": "cloudIdentity",
  "defaultEnabled": true,
  "rules": [
    {
      "id": "0ab24298-637b-4a76-b8c4-7344828f8e59",
      "name": "AWS VPC DHCP Options Association Modified",
      "score": 1
    }
  ],
  "threshold": {
    "targetScore": 1,
    "withinSeconds": 360,
    "dedupSeconds": 360
  },
  "requiredProducts": [
    [
      "sct",
      "scm",
      "tlc|aws|XDR for Cloud - AWS CloudTrail"
    ]
  ],
  "tags": [
    "mitre.t1578"
  ],
  "playbooks": [
    {
      "id": "a4c36882-115b-4296-a5e3-051fc303e0ca",
      "name": "Default Playbook",
      "provider": "WORKBENCH",
      "type": "DETECTION"
    },
    {
      "id": "f87e38bc-b0a9-4997-8b6a-d0762a7bcace",
      "name": "Generic file/ip/url/email investigation",
      "provider": "AIR",
      "type": "AUTOMATED_RESPONSE"
    }
  ],
  "visibleLevel": 1,
  "globalModel": true,
  "silent": false,
  "author": "Sunil Bharti",
  "team": "Cloud One",
  "date": "2025/07/09",
  "lastUpdate": "2025-07-29T15:07:44.000Z"
}