{
  "schemaVersion": "1.0",
  "id": "7fa42009-9cea-4242-a027-85477dbd623e",
  "name": "Dasan GPON Router Authentication Bypass",
  "description": "Check Point Security detection for Dasan GPON Router Authentication Bypass",
  "scope": "endpoint",
  "riskLevel": "medium",
  "rules": [
    {
      "id": "8a240f1d-c8bd-40ed-8330-618dfa18f5d6",
      "name": "Dasan GPON Router Authentication Bypass",
      "score": 1
    }
  ],
  "threshold": {
    "targetScore": 1,
    "withinSeconds": 120,
    "dedupSeconds": 120
  },
  "requiredProducts": [
    [
      "tlc|Check Point"
    ]
  ],
  "tags": [
    "mitre.t1190"
  ],
  "playbooks": [
    {
      "id": "a4c36882-115b-4296-a5e3-051fc303e0ca",
      "name": "Default Playbook",
      "provider": "WORKBENCH",
      "type": "DETECTION"
    },
    {
      "id": "f87e38bc-b0a9-4997-8b6a-d0762a7bcace",
      "name": "Generic file/ip/url/email investigation",
      "provider": "AIR",
      "type": "AUTOMATED_RESPONSE"
    }
  ],
  "visibleLevel": 51,
  "globalModel": true,
  "silent": true,
  "author": "Mark Chester De Quiroz",
  "team": "Third Party Operations",
  "date": "2025/12/11",
  "lastUpdate": "2026-01-15T01:45:40.000Z"
}