{
  "schemaVersion": "1.0",
  "id": "d46ee74f-bf42-455c-b959-b236baa33a27",
  "name": "File Was Blocked By File Filter",
  "description": "Fortinet detection - File was blocked by file filter",
  "riskLevel": "low",
  "scope": "endpoint",
  "rules": [
    {
      "id": "6d7d3373-4cd2-47c7-a335-c1fd2a12e709",
      "name": "File Was Blocked By File Filter",
      "score": 1
    }
  ],
  "threshold": {
    "targetScore": 1,
    "withinSeconds": 3000,
    "dedupSeconds": 3000
  },
  "requiredProducts": [
    [
      "tlc|Fortinet"
    ]
  ],
  "tags": [],
  "playbooks": [
    {
      "id": "a4c36882-115b-4296-a5e3-051fc303e0ca",
      "name": "Default Playbook",
      "provider": "WORKBENCH",
      "type": "DETECTION"
    },
    {
      "id": "f87e38bc-b0a9-4997-8b6a-d0762a7bcace",
      "name": "Generic file/ip/url/email investigation",
      "provider": "AIR",
      "type": "AUTOMATED_RESPONSE"
    }
  ],
  "visibleLevel": 51,
  "globalModel": true,
  "silent": true,
  "author": "James Vargas",
  "team": "DDI",
  "date": "2024/12/04",
  "lastUpdate": "2025-01-06T03:41:40.000Z"
}