{
  "schemaVersion": "1.0",
  "id": "37f06140-dbf6-404f-a017-bdcbc91ed14f",
  "name": "AWS EventBridge Target Association",
  "description": "Detects when a new target is associated with an EventBridge rule, potentially linking a rule to a Lambda or other service to trigger actions.",
  "filterSets": [
    [
      {
        "id": "e2b92b0b-ff48-49cd-964f-8393c4c9b0f2",
        "name": "AWS EventBridge Target Association",
        "highlight": true
      }
    ]
  ],
  "threshold": {
    "targetOccurrence": 1,
    "withinSeconds": 360,
    "dedupSeconds": 360
  },
  "requiredProducts": [
    [
      "sct",
      "scm",
      "tlc|aws|XDR for Cloud - AWS CloudTrail"
    ]
  ],
  "author": "Christopher Ordonez & Sunil Bharti",
  "team": "Cloud One",
  "date": "2024/08/21",
  "lastUpdate": "2025-06-20T03:23:39.000Z"
}