{
  "schemaVersion": "1.0",
  "id": "0cc23bd4-f869-4f40-8b52-8d05f1b1de0f",
  "name": "Credential Access via Sensitive Unix File Combination",
  "description": "Attempts to read Unix files that contain user credentials and other sensitive information were detected on an endpoint.",
  "filterSets": [
    [
      {
        "id": "421d1726-10d9-4144-9e87-0e23e87fb9ed",
        "name": "Read Access On Unix Password File",
        "highlight": true
      },
      {
        "id": "6682ff7d-6faf-4b93-abfc-4faf04818457",
        "name": "Read Access On Unix Bash History",
        "highlight": true
      }
    ],
    [
      {
        "id": "421d1726-10d9-4144-9e87-0e23e87fb9ed",
        "name": "Read Access On Unix Password File",
        "highlight": true
      },
      {
        "id": "3f3e030d-d43d-4117-95c0-ff010b056632",
        "name": "Read Access On Unix Shadow File",
        "highlight": true
      }
    ],
    [
      {
        "id": "6682ff7d-6faf-4b93-abfc-4faf04818457",
        "name": "Read Access On Unix Bash History",
        "highlight": true
      },
      {
        "id": "3f3e030d-d43d-4117-95c0-ff010b056632",
        "name": "Read Access On Unix Shadow File",
        "highlight": true
      }
    ]
  ],
  "threshold": {
    "targetOccurrence": 1,
    "withinSeconds": 7200,
    "dedupSeconds": 7200
  },
  "requiredProducts": [
    [
      "sds",
      "xes"
    ]
  ],
  "author": "Nitesh Surana",
  "team": "Cloud One",
  "date": "2021/05/18",
  "lastUpdate": "2024-07-25T20:20:21.000Z"
}