{
  "schemaVersion": "1.0",
  "id": "9802df5b-fa05-4431-8a05-4fdceb677d32",
  "name": "Impossible Travel Pattern Observed in Login Activity",
  "description": "User account has two successful sign-in attempts originating from geographically distant locations occurring within a time period that is too short to complete travel between the first location to the second, indicating a possible account compromise.",
  "filterSets": [
    [
      {
        "id": "761c3208-5927-4547-8418-245551b78b11",
        "name": "Impossible Travel Pattern Observed in Login Activity",
        "highlight": true
      }
    ]
  ],
  "threshold": {
    "targetOccurrence": 1,
    "withinSeconds": 3600,
    "dedupSeconds": 3600
  },
  "requiredProducts": [
    [
      "aad",
      "sca"
    ]
  ],
  "author": "Jack Walsh",
  "team": "EU-IR",
  "date": "2026/02/03",
  "lastUpdate": "2026-02-13T08:49:14.000Z"
}