{
  "schemaVersion": "1.0",
  "id": "19c629d2-f8f4-4b81-9b03-6e564d998af7",
  "name": "Possible Malicious Download from a Suspicious Website",
  "description": "Detects a possible malicious download from websites containing a suspicious TLD (Top Level Domain)",
  "filterSets": [
    [
      {
        "id": "5ee1ef1a-878d-4fda-917c-25bb02088d75",
        "name": "Possible Phishing from a Suspicious Top Level Domain",
        "highlight": true
      },
      {
        "id": "999f7884-8641-40b6-9f7c-3c649ca8b9de",
        "name": "Possible HTTP Malicious Payload Detection",
        "highlight": true
      }
    ]
  ],
  "threshold": {
    "targetOccurrence": 1,
    "withinSeconds": 120,
    "dedupSeconds": 120
  },
  "requiredProducts": [
    [
      "tlc|Palo Alto Networks"
    ]
  ],
  "author": "Andre Filipe Codod",
  "team": "Third Party Operations",
  "date": "2025/03/20",
  "lastUpdate": "2025-05-27T22:40:51.000Z"
}